absfuyu_res/__init__.py
absfuyu_res/passwordlib_res.pkl
absfuyu_res-0.0.3.dist-info/LICENSE
absfuyu_res-0.0.3.dist-info/METADATA
absfuyu_res-0.0.3.dist-info/WHEEL
absfuyu_res-0.0.3.dist-info/top_level.txt
absfuyu_res-0.0.3.dist-info/RECORD
