Metadata-Version: 2.1
Name: absfuyu-res
Version: 0.0.3
Summary: Resources for absfuyu package
Author: somewhatcold (AbsoluteWinter)
License: MIT License
Project-URL: Homepage, https://github.com/AbsoluteWinter/absfuyu-res
Project-URL: Documentation, https://absolutewinter.github.io/absfuyu
Keywords: utilities
Classifier: Programming Language :: Python :: 3
Classifier: Programming Language :: Python :: 3.8
Classifier: Programming Language :: Python :: 3.9
Classifier: Programming Language :: Python :: 3.10
Classifier: Programming Language :: Python :: 3.11
Classifier: Programming Language :: Python :: 3.12
Classifier: Programming Language :: Python :: 3 :: Only
Classifier: License :: OSI Approved :: MIT License
Classifier: Operating System :: OS Independent
Classifier: Natural Language :: English
Classifier: Intended Audience :: Developers
Classifier: Topic :: Utilities
Requires-Python: <4,>=3.8
License-File: LICENSE
Requires-Dist: importlib-resources ; python_version < "3.11"
